{"schema": ["lcsc", "mfr", "joints", "manufacturer", "description", "datasheet", "price", "images", "url", "attributes"], "components": [["C99005", "TP1542A-SR", 8, "3PEAK", "CMOS 2 2.1V ~ 6V 110uA 1.3MHz 0.7 V/us SOIC-8_150mil Low Power OpAmps RoHS", "https://datasheet.lcsc.com/lcsc/1809281614_3PEAK-TP1542A-SR_C99005.pdf", [{"qFrom": 1, "qTo": 9, "price": 0.295384615}, {"qFrom": 10, "qTo": 13, "price": 0.227692308}, {"qFrom": 14, "qTo": 15, "price": 0.227692308}, {"qFrom": 16, "qTo": 19, "price": 0.227692308}, {"qFrom": 20, "qTo": 28, "price": 0.227692308}, {"qFrom": 29, "qTo": 29, "price": 0.227692308}, {"qFrom": 30, "qTo": 99, "price": 0.121538462}, {"qFrom": 100, "qTo": null, "price": 0.107692308}], [], null, {"Basic/Extended": {"format": "${default}", "primary": "default", "values": {"default": ["Extended", "string"]}}, "Package": {"format": "${default}", "primary": "default", "values": {"default": ["SOIC-8_3.9x4.9x1.27P", "string"]}}, "Status": {"format": "${default}", "primary": "default", "values": {"default": ["-", "string"]}}}], ["C83409", "SGM8541XN5/TR", 5, "SGMICRO", "CMOS 1 2.1V ~ 5.5V 89uA 1.1MHz 0.52 V/us SOT-23-5 Low Power OpAmps RoHS", "https://datasheet.lcsc.com/lcsc/1811091414_SGMICRO-SGM8541XN5-TR_C83409.pdf", [{"qFrom": 1, "qTo": 49, "price": 0.204923077}, {"qFrom": 50, "qTo": null, "price": 0.132769231}], [], null, {"Basic/Extended": {"format": "${default}", "primary": "default", "values": {"default": ["Extended", "string"]}}, "Package": {"format": "${default}", "primary": "default", "values": {"default": ["SOT-23-5", "string"]}}, "Status": {"format": "${default}", "primary": "default", "values": {"default": ["-", "string"]}}}], ["C99007", "TP1541A-TR", 5, "3PEAK", "CMOS 1 2.1V ~ 6V 110uA 1.3MHz 0.7 V/us SOT-23-5 Low Power OpAmps RoHS", "https://datasheet.lcsc.com/lcsc/1809281614_3PEAK-TP1541A-TR_C99007.pdf", [{"qFrom": 1, "qTo": 49, "price": 0.178153846}, {"qFrom": 50, "qTo": null, "price": 0.115384615}], [], null, {"Basic/Extended": {"format": "${default}", "primary": "default", "values": {"default": ["Extended", "string"]}}, "Package": {"format": "${default}", "primary": "default", "values": {"default": ["SOT-23-5", "string"]}}, "Status": {"format": "${default}", "primary": "default", "values": {"default": ["-", "string"]}}}], ["C446025", "TLV2252AIDR", 8, "Texas Instruments", "SOIC-8 Low Power OpAmps RoHS", "https://datasheet.lcsc.com/szlcsc/1912111437_Texas-Instruments-TLV2252AIDR_C446025.pdf", [{"qFrom": 1, "qTo": 9, "price": 1.366153846}, {"qFrom": 10, "qTo": 29, "price": 1.010769231}, {"qFrom": 30, "qTo": 99, "price": 0.944615385}, {"qFrom": 100, "qTo": 499, "price": 0.88}, {"qFrom": 500, "qTo": 999, "price": 0.850769231}, {"qFrom": 1000, "qTo": 1999, "price": 0.836923077}, {"qFrom": 2000, "qTo": 3999, "price": 0.826153846}, {"qFrom": 4000, "qTo": null, "price": 0.818461538}], [], null, {"Basic/Extended": {"format": "${default}", "primary": "default", "values": {"default": ["Extended", "string"]}}, "Package": {"format": "${default}", "primary": "default", "values": {"default": ["SOIC-8_3.9x4.9x1.27P", "string"]}}, "Status": {"format": "${default}", "primary": "default", "values": {"default": ["-", "string"]}}}], ["C431312", "GS8541-TR", 5, "Gainsil", "SOT23-5 Low Power OpAmps RoHS", "https://datasheet.lcsc.com/szlcsc/1912111437_Gainsil-GS8541-TR_C431312.pdf", [{"qFrom": 5, "qTo": 45, "price": 0.111384615}, {"qFrom": 50, "qTo": 145, "price": 0.084461538}, {"qFrom": 150, "qTo": 495, "price": 0.079538462}, {"qFrom": 500, "qTo": 2495, "price": 0.074615385}, {"qFrom": 2500, "qTo": 4995, "price": 0.072461538}, {"qFrom": 5000, "qTo": null, "price": 0.071384615}], ["https://assets.lcsc.com/images/lcsc/900x900/20191030_Gainsil-GS8541-TR_C431312_front.jpg", "https://assets.lcsc.com/images/lcsc/900x900/20191030_Gainsil-GS8541-TR_C431312_back.jpg", "https://assets.lcsc.com/images/lcsc/900x900/20191030_Gainsil-GS8541-TR_C431312_blank.jpg", "https://assets.lcsc.com/images/auth/1625749828876_11403.jpg"], "https://lcsc.com/product-detail/Operational-Amplifier_Gainsil-GS8541-TR_C431312.html", {"Slew Rate\uff08SR\uff09": {"format": "${default}", "primary": "default", "values": {"default": ["-", "string"]}}, "Number of Circuits": {"format": "${default}", "primary": "default", "values": {"default": ["-", "string"]}}, "Operating Temperature": {"format": "${default}", "primary": "default", "values": {"default": ["-", "string"]}}, "Gain Bandwidth Product\uff08GBP\uff09": {"format": "${default}", "primary": "default", "values": {"default": ["-", "string"]}}, "-3db Bandwidth\uff08G=1\uff09": {"format": "${default}", "primary": "default", "values": {"default": ["-", "string"]}}, "Output Type": {"format": "${default}", "primary": "default", "values": {"default": ["-", "string"]}}, "Supply Voltage\uff08Single\uff09": {"format": "${default}", "primary": "default", "values": {"default": ["-", "string"]}}, "Current - Input Bias\uff08Ib\uff09": {"format": "${default}", "primary": "default", "values": {"default": ["-", "string"]}}, "Iq per channel (Typ)": {"format": "${default}", "primary": "default", "values": {"default": ["-", "string"]}}, "Voltage - Input Offset\uff08Vos\uff09": {"format": "${default}", "primary": "default", "values": {"default": ["-", "string"]}}, "Amplifier Type": {"format": "${default}", "primary": "default", "values": {"default": ["-", "string"]}}, "Basic/Extended": {"format": "${default}", "primary": "default", "values": {"default": ["Extended", "string"]}}, "Package": {"format": "${default}", "primary": "default", "values": {"default": ["SOT-23-5", "string"]}}, "Status": {"format": "${default}", "primary": "default", "values": {"default": ["-", "string"]}}}], ["C294593", "GS333-TR", 5, "Gainsil", " ", "https://datasheet.lcsc.com/lcsc/1809290416_Gainsil-GS333-TR_C294593.pdf", [{"qFrom": 1, "qTo": 9, "price": 0.316723077}, {"qFrom": 10, "qTo": 29, "price": 0.239846154}, {"qFrom": 30, "qTo": 99, "price": 0.225692308}, {"qFrom": 100, "qTo": 499, "price": 0.211538462}, {"qFrom": 500, "qTo": 999, "price": 0.205384615}, {"qFrom": 1000, "qTo": 1999, "price": 0.202153846}, {"qFrom": 2000, "qTo": 3999, "price": 0.199846154}, {"qFrom": 4000, "qTo": null, "price": 0.198307692}], [], null, {"Basic/Extended": {"format": "${default}", "primary": "default", "values": {"default": ["Extended", "string"]}}, "Package": {"format": "${default}", "primary": "default", "values": {"default": ["SOT-23-5", "string"]}}, "Status": {"format": "${default}", "primary": "default", "values": {"default": ["-", "string"]}}}], ["C181719", "AD8031ARTZ-REEL", 5, "Analog Devices", "Voltage Feedback 1 2.7V ~ 12V, \u00b11.35V ~ 6V 80MHz(-3dB) 35 V/us SOT-23-5 Low Power OpAmps RoHS", "https://datasheet.lcsc.com/lcsc/1810011018_Analog-Devices-AD8031ARTZ-REEL_C181719.pdf", [{"qFrom": 1, "qTo": 9, "price": 2.623076923}, {"qFrom": 10, "qTo": 29, "price": 1.958461538}, {"qFrom": 30, "qTo": 99, "price": 1.836923077}, {"qFrom": 100, "qTo": 499, "price": 1.715384615}, {"qFrom": 500, "qTo": 999, "price": 1.66}, {"qFrom": 1000, "qTo": 1999, "price": 1.633846154}, {"qFrom": 2000, "qTo": 3999, "price": 1.613846154}, {"qFrom": 4000, "qTo": null, "price": 1.6}], [], null, {"Basic/Extended": {"format": "${default}", "primary": "default", "values": {"default": ["Extended", "string"]}}, "Package": {"format": "${default}", "primary": "default", "values": {"default": ["SOT-23-5", "string"]}}, "Status": {"format": "${default}", "primary": "default", "values": {"default": ["-", "string"]}}}], ["C431313", "GS8542-SR", 8, "Gainsil", "SOP-8 Low Power OpAmps RoHS", "https://datasheet.lcsc.com/lcsc/1912112237_Gainsil-GS8542-SR_C431313.pdf", [{"qFrom": 5, "qTo": 45, "price": 0.127384615}, {"qFrom": 50, "qTo": 145, "price": 0.096615385}, {"qFrom": 150, "qTo": 495, "price": 0.090923077}, {"qFrom": 500, "qTo": 2495, "price": 0.085384615}, {"qFrom": 2500, "qTo": 4995, "price": 0.082769231}, {"qFrom": 5000, "qTo": null, "price": 0.081538462}], ["https://assets.lcsc.com/images/lcsc/900x900/20191129_Gainsil-GS8542-SR_C431313_front.jpg", "https://assets.lcsc.com/images/lcsc/900x900/20191129_Gainsil-GS8542-SR_C431313_back.jpg", "https://assets.lcsc.com/images/lcsc/900x900/20191129_Gainsil-GS8542-SR_C431313_blank.jpg", "https://assets.lcsc.com/images/auth/1625749828876_11403.jpg"], "https://lcsc.com/product-detail/Operational-Amplifier_Gainsil-GS8542-SR_C431313.html", {"Slew Rate\uff08SR\uff09": {"format": "${default}", "primary": "default", "values": {"default": ["-", "string"]}}, "Number of Circuits": {"format": "${default}", "primary": "default", "values": {"default": ["-", "string"]}}, "Operating Temperature": {"format": "${default}", "primary": "default", "values": {"default": ["-", "string"]}}, "Gain Bandwidth Product\uff08GBP\uff09": {"format": "${default}", "primary": "default", "values": {"default": ["-", "string"]}}, "-3db Bandwidth\uff08G=1\uff09": {"format": "${default}", "primary": "default", "values": {"default": ["-", "string"]}}, "Output Type": {"format": "${default}", "primary": "default", "values": {"default": ["-", "string"]}}, "Supply Voltage\uff08Single\uff09": {"format": "${default}", "primary": "default", "values": {"default": ["-", "string"]}}, "Current - Input Bias\uff08Ib\uff09": {"format": "${default}", "primary": "default", "values": {"default": ["-", "string"]}}, "Iq per channel (Typ)": {"format": "${default}", "primary": "default", "values": {"default": ["-", "string"]}}, "Voltage - Input Offset\uff08Vos\uff09": {"format": "${default}", "primary": "default", "values": {"default": ["-", "string"]}}, "Amplifier Type": {"format": "${default}", "primary": "default", "values": {"default": ["-", "string"]}}, "Basic/Extended": {"format": "${default}", "primary": "default", "values": {"default": ["Extended", "string"]}}, "Package": {"format": "${default}", "primary": "default", "values": {"default": ["SOP-8_3.9x4.9x1.27P", "string"]}}, "Status": {"format": "${default}", "primary": "default", "values": {"default": ["-", "string"]}}}]], "category": "Amplifiers", "subcategory": "Low Power OpAmps"}