{"schema": ["lcsc", "mfr", "joints", "manufacturer", "description", "datasheet", "price", "images", "url", "attributes"], "components": [["C145496", "CZB06S04100050HEA", 4, "Vishay Intertech", "SMD-4 RF attenuator ROHS", "https://datasheet.lcsc.com/lcsc/1804162320_Vishay-Intertech-CZB06S04100050HEA_C145496.pdf", [{"qFrom": 1, "qTo": 9, "price": 0.117076923}, {"qFrom": 10, "qTo": 29, "price": 0.114153846}, {"qFrom": 30, "qTo": 99, "price": 0.112153846}, {"qFrom": 100, "qTo": 499, "price": 0.110153846}, {"qFrom": 500, "qTo": null, "price": 0.110153846}], ["https://assets.lcsc.com/images/lcsc/900x900/20180914_Vishay-Intertech-CZB06S04100050HEA_C145496_front.jpg", "https://assets.lcsc.com/images/lcsc/900x900/20180914_Vishay-Intertech-CZB06S04100050HEA_C145496_back.jpg", "https://assets.lcsc.com/images/lcsc/900x900/20180914_Vishay-Intertech-CZB06S04100050HEA_C145496_blank.jpg"], "https://lcsc.com/product-detail/RF-attenuator_Vishay-Intertech-CZB06S04100050HEA_C145496.html", {"Frequency Range": {"format": "${default}", "primary": "default", "values": {"default": ["-", "string"]}}, "Attenuation Value": {"format": "${default}", "primary": "default", "values": {"default": ["-", "string"]}}, "Impedance": {"format": "${default}", "primary": "default", "values": {"default": ["-", "string"]}}, "Power": {"format": "${power}", "default": "power", "values": {"power": ["NaN", "power"]}}, "Basic/Extended": {"format": "${default}", "primary": "default", "values": {"default": ["Extended", "string"]}}, "Package": {"format": "${default}", "primary": "default", "values": {"default": ["SMD-4_4.6x6.5x2.54P", "string"]}}, "Status": {"format": "${default}", "primary": "default", "values": {"default": ["-", "string"]}}}], ["C662145", "HMC273AMS10GETR", 10, "Analog Devices", "MSOP-10 RF attenuator ROHS", "https://datasheet.lcsc.com/lcsc/2006241739_Analog-Devices-HMC273AMS10GETR_C662145.pdf", [{"qFrom": 1, "qTo": 9, "price": 10.309230769}, {"qFrom": 10, "qTo": 29, "price": 10.309230769}, {"qFrom": 30, "qTo": 199, "price": 10.309230769}, {"qFrom": 200, "qTo": 499, "price": 3.989230769}, {"qFrom": 500, "qTo": 999, "price": 3.849230769}, {"qFrom": 1000, "qTo": null, "price": 3.78}], [], "https://lcsc.com/product-detail/RF-attenuator_Analog-Devices-HMC273AMS10GETR_C662145.html", {"Frequency Range": {"format": "${default}", "primary": "default", "values": {"default": ["-", "string"]}}, "Attenuation Value": {"format": "${default}", "primary": "default", "values": {"default": ["-", "string"]}}, "Impedance": {"format": "${default}", "primary": "default", "values": {"default": ["-", "string"]}}, "Power": {"format": "${power}", "default": "power", "values": {"power": ["NaN", "power"]}}, "Basic/Extended": {"format": "${default}", "primary": "default", "values": {"default": ["Extended", "string"]}}, "Package": {"format": "${default}", "primary": "default", "values": {"default": ["SOP-10", "string"]}}, "Status": {"format": "${default}", "primary": "default", "values": {"default": ["-", "string"]}}}], ["C470929", "PE43711B-Z", 25, "PSemi", "QFN-24 RF attenuator ROHS", "https://datasheet.lcsc.com/lcsc/1912171815_PSemi-PE43711B-Z_C470929.pdf", [{"qFrom": 1, "qTo": 9, "price": 6.493846154}, {"qFrom": 10, "qTo": 29, "price": 4.956923077}, {"qFrom": 30, "qTo": 99, "price": 4.673846154}, {"qFrom": 100, "qTo": 499, "price": 4.390769231}, {"qFrom": 500, "qTo": 999, "price": 4.266153846}, {"qFrom": 1000, "qTo": 1999, "price": 4.203076923}, {"qFrom": 2000, "qTo": 3999, "price": 4.156923077}, {"qFrom": 4000, "qTo": null, "price": 4.126153846}], ["https://assets.lcsc.com/images/lcsc/900x900/20200113_PSemi-PE43711B-Z_C470929_front.jpg", "https://assets.lcsc.com/images/lcsc/900x900/20200113_PSemi-PE43711B-Z_C470929_back.jpg", "https://assets.lcsc.com/images/lcsc/900x900/20200113_PSemi-PE43711B-Z_C470929_blank.jpg"], "https://lcsc.com/product-detail/RF-attenuator_PSemi-PE43711B-Z_C470929.html", {"Frequency Range": {"format": "${default}", "primary": "default", "values": {"default": ["-", "string"]}}, "Attenuation Value": {"format": "${default}", "primary": "default", "values": {"default": ["-", "string"]}}, "Impedance": {"format": "${default}", "primary": "default", "values": {"default": ["-", "string"]}}, "Power": {"format": "${power}", "default": "power", "values": {"power": ["NaN", "power"]}}, "Basic/Extended": {"format": "${default}", "primary": "default", "values": {"default": ["Extended", "string"]}}, "Package": {"format": "${default}", "primary": "default", "values": {"default": ["QFN-24", "string"]}}, "Status": {"format": "${default}", "primary": "default", "values": {"default": ["-", "string"]}}}], ["C500480", "PE4312C-Z", 21, "PSemi", "QFN-20(4x4) RF attenuator ROHS", "https://datasheet.lcsc.com/lcsc/2003241709_PSemi-PE4312C-Z_C500480.pdf", [{"qFrom": 1, "qTo": 9, "price": 2.429230769}, {"qFrom": 10, "qTo": 29, "price": 1.852307692}, {"qFrom": 30, "qTo": 99, "price": 1.746153846}, {"qFrom": 100, "qTo": 499, "price": 1.64}, {"qFrom": 500, "qTo": 999, "price": 1.593846154}, {"qFrom": 1000, "qTo": 1999, "price": 1.569230769}, {"qFrom": 2000, "qTo": 3999, "price": 1.552307692}, {"qFrom": 4000, "qTo": null, "price": 1.541538462}], ["https://assets.lcsc.com/images/lcsc/900x900/20200402_PSemi-PE4312C-Z_C500480_front.jpg", "https://assets.lcsc.com/images/lcsc/900x900/20200402_PSemi-PE4312C-Z_C500480_back.jpg", "https://assets.lcsc.com/images/lcsc/900x900/20200402_PSemi-PE4312C-Z_C500480_blank.jpg"], "https://lcsc.com/product-detail/RF-attenuator_PSemi-PE4312C-Z_C500480.html", {"Frequency Range": {"format": "${default}", "primary": "default", "values": {"default": ["-", "string"]}}, "Attenuation Value": {"format": "${default}", "primary": "default", "values": {"default": ["-", "string"]}}, "Impedance": {"format": "${default}", "primary": "default", "values": {"default": ["-", "string"]}}, "Power": {"format": "${power}", "default": "power", "values": {"power": ["NaN", "power"]}}, "Basic/Extended": {"format": "${default}", "primary": "default", "values": {"default": ["Extended", "string"]}}, "Package": {"format": "${default}", "primary": "default", "values": {"default": ["QFN-20", "string"]}}, "Status": {"format": "${default}", "primary": "default", "values": {"default": ["-", "string"]}}}], ["C153012", "EXB24AT6AR5X", 4, "PANASONIC", "Surface Mount RF attenuator ROHS", "https://datasheet.lcsc.com/lcsc/1810171025_PANASONIC-EXB24AT6AR5X_C153012.pdf", [{"qFrom": 1, "qTo": 9, "price": 0.102769231}, {"qFrom": 10, "qTo": 29, "price": 0.100461538}, {"qFrom": 30, "qTo": 99, "price": 0.098923077}, {"qFrom": 100, "qTo": 499, "price": 0.097384615}, {"qFrom": 500, "qTo": null, "price": 0.097384615}], ["https://assets.lcsc.com/images/lcsc/900x900/20180914_PANASONIC-EXB24AT6AR5X_C153012_front.jpg", "https://assets.lcsc.com/images/lcsc/900x900/20180914_PANASONIC-EXB24AT6AR5X_C153012_back.jpg", "https://assets.lcsc.com/images/lcsc/900x900/20180914_PANASONIC-EXB24AT6AR5X_C153012_blank.jpg"], "https://lcsc.com/product-detail/RF-attenuator_PANASONIC-EXB24AT6AR5X_C153012.html", {"Frequency Range": {"format": "${default}", "primary": "default", "values": {"default": ["-", "string"]}}, "Attenuation Value": {"format": "${default}", "primary": "default", "values": {"default": ["-", "string"]}}, "Impedance": {"format": "${default}", "primary": "default", "values": {"default": ["-", "string"]}}, "Power": {"format": "${power}", "default": "power", "values": {"power": ["NaN", "power"]}}, "Basic/Extended": {"format": "${default}", "primary": "default", "values": {"default": ["Extended", "string"]}}, "Package": {"format": "${default}", "primary": "default", "values": {"default": ["RF-SMD", "string"]}}, "Status": {"format": "${default}", "primary": "default", "values": {"default": ["-", "string"]}}}], ["C153025", "EXB24AT5AR3X", 4, "PANASONIC", "Surface Mount RF attenuator ROHS", "https://datasheet.lcsc.com/lcsc/1810171025_PANASONIC-EXB24AT5AR3X_C153025.pdf", [{"qFrom": 1, "qTo": 9, "price": 0.213384615}, {"qFrom": 10, "qTo": 29, "price": 0.162953846}, {"qFrom": 30, "qTo": 99, "price": 0.153692308}, {"qFrom": 100, "qTo": 499, "price": 0.144461538}, {"qFrom": 500, "qTo": 999, "price": 0.140307692}, {"qFrom": 1000, "qTo": null, "price": 0.138307692}], ["https://assets.lcsc.com/images/lcsc/900x900/20180914_PANASONIC-EXB24AT5AR3X_C153025_front.jpg", "https://assets.lcsc.com/images/lcsc/900x900/20180914_PANASONIC-EXB24AT5AR3X_C153025_back.jpg", "https://assets.lcsc.com/images/lcsc/900x900/20180914_PANASONIC-EXB24AT5AR3X_C153025_blank.jpg"], "https://lcsc.com/product-detail/RF-attenuator_PANASONIC-EXB24AT5AR3X_C153025.html", {"Frequency Range": {"format": "${default}", "primary": "default", "values": {"default": ["-", "string"]}}, "Attenuation Value": {"format": "${default}", "primary": "default", "values": {"default": ["-", "string"]}}, "Impedance": {"format": "${default}", "primary": "default", "values": {"default": ["-", "string"]}}, "Power": {"format": "${power}", "default": "power", "values": {"power": ["NaN", "power"]}}, "Basic/Extended": {"format": "${default}", "primary": "default", "values": {"default": ["Extended", "string"]}}, "Package": {"format": "${default}", "primary": "default", "values": {"default": ["RF-SMD", "string"]}}, "Status": {"format": "${default}", "primary": "default", "values": {"default": ["-", "string"]}}}], ["C153044", "EXB24AT4AR3X", 4, "PANASONIC", "Surface Mount RF attenuator ROHS", "https://datasheet.lcsc.com/lcsc/1810171025_PANASONIC-EXB24AT4AR3X_C153044.pdf", [{"qFrom": 1, "qTo": 9, "price": 0.121692308}, {"qFrom": 10, "qTo": 29, "price": 0.118615385}, {"qFrom": 30, "qTo": 99, "price": 0.116461538}, {"qFrom": 100, "qTo": 499, "price": 0.114461538}, {"qFrom": 500, "qTo": null, "price": 0.114461538}], ["https://assets.lcsc.com/images/lcsc/900x900/20180914_PANASONIC-EXB24AT4AR3X_C153044_front.jpg", "https://assets.lcsc.com/images/lcsc/900x900/20180914_PANASONIC-EXB24AT4AR3X_C153044_back.jpg", "https://assets.lcsc.com/images/lcsc/900x900/20180914_PANASONIC-EXB24AT4AR3X_C153044_blank.jpg"], "https://lcsc.com/product-detail/RF-attenuator_PANASONIC-EXB24AT4AR3X_C153044.html", {"Frequency Range": {"format": "${default}", "primary": "default", "values": {"default": ["-", "string"]}}, "Attenuation Value": {"format": "${default}", "primary": "default", "values": {"default": ["-", "string"]}}, "Impedance": {"format": "${default}", "primary": "default", "values": {"default": ["-", "string"]}}, "Power": {"format": "${power}", "default": "power", "values": {"power": ["NaN", "power"]}}, "Basic/Extended": {"format": "${default}", "primary": "default", "values": {"default": ["Extended", "string"]}}, "Package": {"format": "${default}", "primary": "default", "values": {"default": ["RF-SMD", "string"]}}, "Status": {"format": "${default}", "primary": "default", "values": {"default": ["-", "string"]}}}], ["C153046", "EXB24AT1AR3X", 4, "PANASONIC", "Surface Mount RF attenuator ROHS", "https://datasheet.lcsc.com/lcsc/1810171025_PANASONIC-EXB24AT1AR3X_C153046.pdf", [{"qFrom": 1, "qTo": 9, "price": 0.184461538}, {"qFrom": 10, "qTo": 29, "price": 0.137692308}, {"qFrom": 30, "qTo": 99, "price": 0.129230769}, {"qFrom": 100, "qTo": 499, "price": 0.120615385}, {"qFrom": 500, "qTo": 999, "price": 0.116769231}, {"qFrom": 1000, "qTo": null, "price": 0.114923077}], ["https://assets.lcsc.com/images/lcsc/900x900/20180914_PANASONIC-EXB24AT1AR3X_C153046_front.jpg", "https://assets.lcsc.com/images/lcsc/900x900/20180914_PANASONIC-EXB24AT1AR3X_C153046_back.jpg", "https://assets.lcsc.com/images/lcsc/900x900/20180914_PANASONIC-EXB24AT1AR3X_C153046_blank.jpg"], "https://lcsc.com/product-detail/RF-attenuator_PANASONIC-EXB24AT1AR3X_C153046.html", {"Frequency Range": {"format": "${default}", "primary": "default", "values": {"default": ["-", "string"]}}, "Attenuation Value": {"format": "${default}", "primary": "default", "values": {"default": ["-", "string"]}}, "Impedance": {"format": "${default}", "primary": "default", "values": {"default": ["-", "string"]}}, "Power": {"format": "${power}", "default": "power", "values": {"power": ["NaN", "power"]}}, "Basic/Extended": {"format": "${default}", "primary": "default", "values": {"default": ["Extended", "string"]}}, "Package": {"format": "${default}", "primary": "default", "values": {"default": ["RF-SMD", "string"]}}, "Status": {"format": "${default}", "primary": "default", "values": {"default": ["-", "string"]}}}], ["C208023", "HMC655LP2ETR", 7, "Analog Devices", "TDFN-6 RF attenuator ROHS", "https://datasheet.lcsc.com/lcsc/1806102240_Analog-Devices-HMC655LP2ETR_C208023.pdf", [{"qFrom": 1, "qTo": 9, "price": 8.190769231}, {"qFrom": 10, "qTo": 29, "price": 7.109230769}, {"qFrom": 30, "qTo": 99, "price": 6.910769231}, {"qFrom": 100, "qTo": 499, "price": 6.712307692}, {"qFrom": 500, "qTo": 999, "price": 6.624615385}, {"qFrom": 1000, "qTo": null, "price": 6.515384615}], ["https://assets.lcsc.com/images/lcsc/900x900/20180914_Analog-Devices-HMC655LP2ETR_C208023_front.jpg", "https://assets.lcsc.com/images/lcsc/900x900/20180914_Analog-Devices-HMC655LP2ETR_C208023_back.jpg", "https://assets.lcsc.com/images/lcsc/900x900/20180914_Analog-Devices-HMC655LP2ETR_C208023_blank.jpg"], "https://lcsc.com/product-detail/RF-attenuator_Analog-Devices-HMC655LP2ETR_C208023.html", {"Frequency Range": {"format": "${default}", "primary": "default", "values": {"default": ["-", "string"]}}, "Attenuation Value": {"format": "${default}", "primary": "default", "values": {"default": ["-", "string"]}}, "Impedance": {"format": "${default}", "primary": "default", "values": {"default": ["-", "string"]}}, "Power": {"format": "${power}", "default": "power", "values": {"power": ["NaN", "power"]}}, "Basic/Extended": {"format": "${default}", "primary": "default", "values": {"default": ["Extended", "string"]}}, "Package": {"format": "${default}", "primary": "default", "values": {"default": ["TDFN-6", "string"]}}, "Status": {"format": "${default}", "primary": "default", "values": {"default": ["-", "string"]}}}], ["C208337", "HMC540SLP3ETR", 17, "Analog Devices", "VFQFN-16 RF attenuator ROHS", "https://datasheet.lcsc.com/lcsc/1806102221_Analog-Devices-HMC540SLP3ETR_C208337.pdf", [{"qFrom": 1, "qTo": 9, "price": 2.536923077}, {"qFrom": 10, "qTo": 29, "price": 1.916923077}, {"qFrom": 30, "qTo": 99, "price": 1.803076923}, {"qFrom": 100, "qTo": 499, "price": 1.690769231}, {"qFrom": 500, "qTo": 999, "price": 1.64}, {"qFrom": 1000, "qTo": null, "price": 1.613846154}], ["https://assets.lcsc.com/images/lcsc/900x900/20180914_Analog-Devices-HMC540SLP3ETR_C208337_front.jpg", "https://assets.lcsc.com/images/lcsc/900x900/20180914_Analog-Devices-HMC540SLP3ETR_C208337_back.jpg", "https://assets.lcsc.com/images/lcsc/900x900/20180914_Analog-Devices-HMC540SLP3ETR_C208337_blank.jpg"], "https://lcsc.com/product-detail/RF-attenuator_Analog-Devices-HMC540SLP3ETR_C208337.html", {"Frequency Range": {"format": "${default}", "primary": "default", "values": {"default": ["-", "string"]}}, "Attenuation Value": {"format": "${default}", "primary": "default", "values": {"default": ["-", "string"]}}, "Impedance": {"format": "${default}", "primary": "default", "values": {"default": ["-", "string"]}}, "Power": {"format": "${power}", "default": "power", "values": {"power": ["NaN", "power"]}}, "Basic/Extended": {"format": "${default}", "primary": "default", "values": {"default": ["Extended", "string"]}}, "Package": {"format": "${default}", "primary": "default", "values": {"default": ["VFQFN-16", "string"]}}, "Status": {"format": "${default}", "primary": "default", "values": {"default": ["-", "string"]}}}], ["C208526", "HMC759LP3E", 17, "Analog Devices", "VFQFN-16 RF attenuator ROHS", "https://datasheet.lcsc.com/lcsc/1806102212_Analog-Devices-HMC759LP3E_C208526.pdf", [{"qFrom": 1, "qTo": 9, "price": 10.426153846}, {"qFrom": 10, "qTo": 29, "price": 8.127692308}, {"qFrom": 30, "qTo": 99, "price": 7.984615385}, {"qFrom": 100, "qTo": 499, "price": 7.841538462}, {"qFrom": 500, "qTo": null, "price": 7.841538462}], ["https://assets.lcsc.com/images/lcsc/900x900/20180914_Analog-Devices-HMC759LP3E_C208526_front.jpg", "https://assets.lcsc.com/images/lcsc/900x900/20180914_Analog-Devices-HMC759LP3E_C208526_back.jpg", "https://assets.lcsc.com/images/lcsc/900x900/20180914_Analog-Devices-HMC759LP3E_C208526_blank.jpg"], "https://lcsc.com/product-detail/RF-attenuator_Analog-Devices-HMC759LP3E_C208526.html", {"Frequency Range": {"format": "${default}", "primary": "default", "values": {"default": ["-", "string"]}}, "Attenuation Value": {"format": "${default}", "primary": "default", "values": {"default": ["-", "string"]}}, "Impedance": {"format": "${default}", "primary": "default", "values": {"default": ["-", "string"]}}, "Power": {"format": "${power}", "default": "power", "values": {"power": ["NaN", "power"]}}, "Basic/Extended": {"format": "${default}", "primary": "default", "values": {"default": ["Extended", "string"]}}, "Package": {"format": "${default}", "primary": "default", "values": {"default": ["VFQFN-16", "string"]}}, "Status": {"format": "${default}", "primary": "default", "values": {"default": ["-", "string"]}}}], ["C208585", "HMC472ALP4ETR", 25, "Analog Devices", "VFQFN-24 RF attenuator ROHS", "https://datasheet.lcsc.com/lcsc/1806102212_Analog-Devices-HMC472ALP4ETR_C208585.pdf", [{"qFrom": 1, "qTo": 9, "price": 3.306153846}, {"qFrom": 10, "qTo": 29, "price": 2.507692308}, {"qFrom": 30, "qTo": 99, "price": 2.36}, {"qFrom": 100, "qTo": 499, "price": 2.213846154}, {"qFrom": 500, "qTo": 999, "price": 2.147692308}, {"qFrom": 1000, "qTo": null, "price": 2.116923077}], ["https://assets.lcsc.com/images/lcsc/900x900/20180914_Analog-Devices-HMC472ALP4ETR_C208585_front.jpg", "https://assets.lcsc.com/images/lcsc/900x900/20180914_Analog-Devices-HMC472ALP4ETR_C208585_back.jpg", "https://assets.lcsc.com/images/lcsc/900x900/20180914_Analog-Devices-HMC472ALP4ETR_C208585_blank.jpg"], "https://lcsc.com/product-detail/RF-attenuator_Analog-Devices-HMC472ALP4ETR_C208585.html", {"Frequency Range": {"format": "${default}", "primary": "default", "values": {"default": ["-", "string"]}}, "Attenuation Value": {"format": "${default}", "primary": "default", "values": {"default": ["-", "string"]}}, "Impedance": {"format": "${default}", "primary": "default", "values": {"default": ["-", "string"]}}, "Power": {"format": "${power}", "default": "power", "values": {"power": ["NaN", "power"]}}, "Basic/Extended": {"format": "${default}", "primary": "default", "values": {"default": ["Extended", "string"]}}, "Package": {"format": "${default}", "primary": "default", "values": {"default": ["QFN-24", "string"]}}, "Status": {"format": "${default}", "primary": "default", "values": {"default": ["-", "string"]}}}], ["C208651", "HMC624ALP4E", 25, "Analog Devices", "VFQFN-24 RF attenuator ROHS", "https://datasheet.lcsc.com/lcsc/1806102212_Analog-Devices-HMC624ALP4E_C208651.pdf", [{"qFrom": 1, "qTo": 9, "price": 5.235384615}, {"qFrom": 10, "qTo": 29, "price": 4.590769231}, {"qFrom": 30, "qTo": 99, "price": 4.470769231}, {"qFrom": 100, "qTo": 499, "price": 4.352307692}, {"qFrom": 500, "qTo": 999, "price": 4.3}, {"qFrom": 1000, "qTo": null, "price": 4.235384615}], ["https://assets.lcsc.com/images/lcsc/900x900/20180914_Analog-Devices-HMC624ALP4E_C208651_front.jpg", "https://assets.lcsc.com/images/lcsc/900x900/20180914_Analog-Devices-HMC624ALP4E_C208651_back.jpg", "https://assets.lcsc.com/images/lcsc/900x900/20180914_Analog-Devices-HMC624ALP4E_C208651_blank.jpg"], "https://lcsc.com/product-detail/RF-attenuator_Analog-Devices-HMC624ALP4E_C208651.html", {"Frequency Range": {"format": "${default}", "primary": "default", "values": {"default": ["-", "string"]}}, "Attenuation Value": {"format": "${default}", "primary": "default", "values": {"default": ["-", "string"]}}, "Impedance": {"format": "${default}", "primary": "default", "values": {"default": ["-", "string"]}}, "Power": {"format": "${power}", "default": "power", "values": {"power": ["NaN", "power"]}}, "Basic/Extended": {"format": "${default}", "primary": "default", "values": {"default": ["Extended", "string"]}}, "Package": {"format": "${default}", "primary": "default", "values": {"default": ["QFN-24", "string"]}}, "Status": {"format": "${default}", "primary": "default", "values": {"default": ["-", "string"]}}}], ["C209364", "HMC472ALP4E", 25, "Analog Devices", "VFQFN-24 RF attenuator ROHS", "https://datasheet.lcsc.com/lcsc/1809081632_Analog-Devices-HMC472ALP4E_C209364.pdf", [{"qFrom": 1, "qTo": 9, "price": 9.28}, {"qFrom": 10, "qTo": 29, "price": 7.992307692}, {"qFrom": 30, "qTo": 99, "price": 7.755384615}, {"qFrom": 100, "qTo": 499, "price": 7.52}, {"qFrom": 500, "qTo": 999, "price": 7.413846154}, {"qFrom": 1000, "qTo": null, "price": 7.284615385}], ["https://assets.lcsc.com/images/lcsc/900x900/20180914_Analog-Devices-HMC472ALP4E_C209364_front.jpg", "https://assets.lcsc.com/images/lcsc/900x900/20180914_Analog-Devices-HMC472ALP4E_C209364_back.jpg", "https://assets.lcsc.com/images/lcsc/900x900/20180914_Analog-Devices-HMC472ALP4E_C209364_blank.jpg"], "https://lcsc.com/product-detail/RF-attenuator_Analog-Devices-HMC472ALP4E_C209364.html", {"Frequency Range": {"format": "${default}", "primary": "default", "values": {"default": ["-", "string"]}}, "Attenuation Value": {"format": "${default}", "primary": "default", "values": {"default": ["-", "string"]}}, "Impedance": {"format": "${default}", "primary": "default", "values": {"default": ["-", "string"]}}, "Power": {"format": "${power}", "default": "power", "values": {"power": ["NaN", "power"]}}, "Basic/Extended": {"format": "${default}", "primary": "default", "values": {"default": ["Extended", "string"]}}, "Package": {"format": "${default}", "primary": "default", "values": {"default": ["QFN-24", "string"]}}, "Status": {"format": "${default}", "primary": "default", "values": {"default": ["-", "string"]}}}], ["C209442", "HMC802ALP3E", 17, "Analog Devices", "VFQFN-16 RF attenuator ROHS", "https://datasheet.lcsc.com/lcsc/1806030442_Analog-Devices-HMC802ALP3E_C209442.pdf", [{"qFrom": 1, "qTo": 9, "price": 5.864615385}, {"qFrom": 10, "qTo": 29, "price": 5.713846154}, {"qFrom": 30, "qTo": 99, "price": 5.613846154}, {"qFrom": 100, "qTo": 499, "price": 5.513846154}, {"qFrom": 500, "qTo": null, "price": 5.513846154}], ["https://assets.lcsc.com/images/lcsc/900x900/20180914_Analog-Devices-HMC802ALP3E_C209442_front.jpg", "https://assets.lcsc.com/images/lcsc/900x900/20180914_Analog-Devices-HMC802ALP3E_C209442_back.jpg", "https://assets.lcsc.com/images/lcsc/900x900/20180914_Analog-Devices-HMC802ALP3E_C209442_blank.jpg"], "https://lcsc.com/product-detail/RF-attenuator_Analog-Devices-HMC802ALP3E_C209442.html", {"Frequency Range": {"format": "${default}", "primary": "default", "values": {"default": ["-", "string"]}}, "Attenuation Value": {"format": "${default}", "primary": "default", "values": {"default": ["-", "string"]}}, "Impedance": {"format": "${default}", "primary": "default", "values": {"default": ["-", "string"]}}, "Power": {"format": "${power}", "default": "power", "values": {"power": ["NaN", "power"]}}, "Basic/Extended": {"format": "${default}", "primary": "default", "values": {"default": ["Extended", "string"]}}, "Package": {"format": "${default}", "primary": "default", "values": {"default": ["VFQFN-16", "string"]}}, "Status": {"format": "${default}", "primary": "default", "values": {"default": ["-", "string"]}}}], ["C2654128", "PE43704B-Z", 33, "PSemi", "VFQFN-32 RF attenuator ROHS", " ", [{"qFrom": 1, "qTo": 9, "price": 15.763076923}, {"qFrom": 10, "qTo": 29, "price": 15.763076923}, {"qFrom": 30, "qTo": 199, "price": 15.763076923}, {"qFrom": 200, "qTo": 499, "price": 6.1}, {"qFrom": 500, "qTo": 999, "price": 5.886153846}, {"qFrom": 1000, "qTo": null, "price": 5.78}], [], "https://lcsc.com/product-detail/RF-attenuator_PSemi-PE43704B-Z_C2654128.html", {"Frequency Range": {"format": "${default}", "primary": "default", "values": {"default": ["-", "string"]}}, "Attenuation Value": {"format": "${default}", "primary": "default", "values": {"default": ["-", "string"]}}, "Impedance": {"format": "${default}", "primary": "default", "values": {"default": ["-", "string"]}}, "Power": {"format": "${power}", "default": "power", "values": {"power": ["NaN", "power"]}}, "Basic/Extended": {"format": "${default}", "primary": "default", "values": {"default": ["Extended", "string"]}}, "Package": {"format": "${default}", "primary": "default", "values": {"default": ["QFN-32", "string"]}}, "Status": {"format": "${default}", "primary": "default", "values": {"default": ["-", "string"]}}}], ["C469033", "RFSA2033TR7", 17, "Qorvo", "QFN_3X3mm RF attenuator ROHS", "https://datasheet.lcsc.com/lcsc/1912141448_Qorvo-RFSA2033TR7_C469033.pdf", [{"qFrom": 1, "qTo": 9, "price": 3.047692308}, {"qFrom": 10, "qTo": 29, "price": 2.616923077}, {"qFrom": 30, "qTo": 99, "price": 2.538461538}, {"qFrom": 100, "qTo": 499, "price": 2.458461538}, {"qFrom": 500, "qTo": 999, "price": 2.423076923}, {"qFrom": 1000, "qTo": 1999, "price": 2.38}, {"qFrom": 2000, "qTo": 3999, "price": 2.347692308}, {"qFrom": 4000, "qTo": null, "price": 2.326153846}], ["https://assets.lcsc.com/images/lcsc/900x900/20200113_Qorvo-RFSA2033TR7_C469033_front.jpg", "https://assets.lcsc.com/images/lcsc/900x900/20200113_Qorvo-RFSA2033TR7_C469033_back.jpg", "https://assets.lcsc.com/images/lcsc/900x900/20200113_Qorvo-RFSA2033TR7_C469033_blank.jpg"], "https://lcsc.com/product-detail/RF-attenuator_Qorvo-RFSA2033TR7_C469033.html", {"Frequency Range": {"format": "${default}", "primary": "default", "values": {"default": ["-", "string"]}}, "Attenuation Value": {"format": "${default}", "primary": "default", "values": {"default": ["-", "string"]}}, "Impedance": {"format": "${default}", "primary": "default", "values": {"default": ["-", "string"]}}, "Power": {"format": "${power}", "default": "power", "values": {"power": ["NaN", "power"]}}, "Basic/Extended": {"format": "${default}", "primary": "default", "values": {"default": ["Extended", "string"]}}, "Package": {"format": "${default}", "primary": "default", "values": {"default": ["QFN_3X3mm", "string"]}}, "Status": {"format": "${default}", "primary": "default", "values": {"default": ["-", "string"]}}}], ["C209550", "HMC656LP2E", 7, "Analog Devices", "TDFN-6 RF attenuator ROHS", "https://datasheet.lcsc.com/lcsc/1806011151_Analog-Devices-HMC656LP2E_C209550.pdf", [{"qFrom": 1, "qTo": 9, "price": 9.115384615}, {"qFrom": 10, "qTo": 29, "price": 7.821538462}, {"qFrom": 30, "qTo": 99, "price": 7.583076923}, {"qFrom": 100, "qTo": 499, "price": 7.346153846}, {"qFrom": 500, "qTo": 999, "price": 7.24}, {"qFrom": 1000, "qTo": null, "price": 7.109230769}], ["https://assets.lcsc.com/images/lcsc/900x900/20180914_Analog-Devices-HMC656LP2E_C209550_front.jpg", "https://assets.lcsc.com/images/lcsc/900x900/20180914_Analog-Devices-HMC656LP2E_C209550_back.jpg", "https://assets.lcsc.com/images/lcsc/900x900/20180914_Analog-Devices-HMC656LP2E_C209550_blank.jpg"], "https://lcsc.com/product-detail/RF-attenuator_Analog-Devices-HMC656LP2E_C209550.html", {"Frequency Range": {"format": "${default}", "primary": "default", "values": {"default": ["-", "string"]}}, "Attenuation Value": {"format": "${default}", "primary": "default", "values": {"default": ["-", "string"]}}, "Impedance": {"format": "${default}", "primary": "default", "values": {"default": ["-", "string"]}}, "Power": {"format": "${power}", "default": "power", "values": {"power": ["NaN", "power"]}}, "Basic/Extended": {"format": "${default}", "primary": "default", "values": {"default": ["Extended", "string"]}}, "Package": {"format": "${default}", "primary": "default", "values": {"default": ["TDFN-6", "string"]}}, "Status": {"format": "${default}", "primary": "default", "values": {"default": ["-", "string"]}}}], ["C661906", "HMC468ALP3ETR", 17, "Analog Devices", "STM-16(3x3) RF attenuator ROHS", "https://datasheet.lcsc.com/lcsc/2006281934_Analog-Devices-HMC468ALP3ETR_C661906.pdf", [{"qFrom": 1, "qTo": 9, "price": 10.978461538}, {"qFrom": 10, "qTo": 29, "price": 10.978461538}, {"qFrom": 30, "qTo": 199, "price": 10.978461538}, {"qFrom": 200, "qTo": 499, "price": 4.249230769}, {"qFrom": 500, "qTo": 999, "price": 4.1}, {"qFrom": 1000, "qTo": null, "price": 4.026153846}], [], "https://lcsc.com/product-detail/RF-attenuator_Analog-Devices-HMC468ALP3ETR_C661906.html", {"Frequency Range": {"format": "${default}", "primary": "default", "values": {"default": ["-", "string"]}}, "Attenuation Value": {"format": "${default}", "primary": "default", "values": {"default": ["-", "string"]}}, "Impedance": {"format": "${default}", "primary": "default", "values": {"default": ["-", "string"]}}, "Power": {"format": "${power}", "default": "power", "values": {"power": ["NaN", "power"]}}, "Basic/Extended": {"format": "${default}", "primary": "default", "values": {"default": ["Extended", "string"]}}, "Package": {"format": "${default}", "primary": "default", "values": {"default": ["SMT-16", "string"]}}, "Status": {"format": "${default}", "primary": "default", "values": {"default": ["-", "string"]}}}], ["C662398", "HMC658LP2ETR", 7, "Analog Devices", "DFN-EP-6 RF attenuator ROHS", "https://datasheet.lcsc.com/lcsc/2006241210_Analog-Devices-HMC658LP2ETR_C662398.pdf", [{"qFrom": 1, "qTo": 9, "price": 10.383076923}, {"qFrom": 10, "qTo": 29, "price": 10.383076923}, {"qFrom": 30, "qTo": 199, "price": 10.383076923}, {"qFrom": 200, "qTo": 499, "price": 4.018461538}, {"qFrom": 500, "qTo": 999, "price": 3.876923077}, {"qFrom": 1000, "qTo": null, "price": 3.807692308}], [], "https://lcsc.com/product-detail/RF-attenuator_Analog-Devices-HMC658LP2ETR_C662398.html", {"Frequency Range": {"format": "${default}", "primary": "default", "values": {"default": ["-", "string"]}}, "Attenuation Value": {"format": "${default}", "primary": "default", "values": {"default": ["-", "string"]}}, "Impedance": {"format": "${default}", "primary": "default", "values": {"default": ["-", "string"]}}, "Power": {"format": "${power}", "default": "power", "values": {"power": ["NaN", "power"]}}, "Basic/Extended": {"format": "${default}", "primary": "default", "values": {"default": ["Extended", "string"]}}, "Package": {"format": "${default}", "primary": "default", "values": {"default": ["DFN-6", "string"]}}, "Status": {"format": "${default}", "primary": "default", "values": {"default": ["-", "string"]}}}], ["C661894", "HMC985ALP4KETR", 25, "Analog Devices", "STM-24(4x4) RF attenuator ROHS", "https://datasheet.lcsc.com/lcsc/2006281821_Analog-Devices-HMC985ALP4KETR_C661894.pdf", [{"qFrom": 1, "qTo": 9, "price": 78.821538462}, {"qFrom": 10, "qTo": 29, "price": 78.821538462}, {"qFrom": 30, "qTo": 199, "price": 78.821538462}, {"qFrom": 200, "qTo": 499, "price": 30.503076923}, {"qFrom": 500, "qTo": 999, "price": 29.430769231}, {"qFrom": 1000, "qTo": null, "price": 28.901538462}], [], "https://lcsc.com/product-detail/RF-attenuator_Analog-Devices-HMC985ALP4KETR_C661894.html", {"Frequency Range": {"format": "${default}", "primary": "default", "values": {"default": ["-", "string"]}}, "Attenuation Value": {"format": "${default}", "primary": "default", "values": {"default": ["-", "string"]}}, "Impedance": {"format": "${default}", "primary": "default", "values": {"default": ["-", "string"]}}, "Power": {"format": "${power}", "default": "power", "values": {"power": ["NaN", "power"]}}, "Basic/Extended": {"format": "${default}", "primary": "default", "values": {"default": ["Extended", "string"]}}, "Package": {"format": "${default}", "primary": "default", "values": {"default": ["SMT-24", "string"]}}, "Status": {"format": "${default}", "primary": "default", "values": {"default": ["-", "string"]}}}], ["C662750", "HMC802ALP3ETR", 17, "Analog Devices", "SMT-16(3x3) RF attenuator ROHS", "https://datasheet.lcsc.com/lcsc/2006241609_Analog-Devices-HMC802ALP3ETR_C662750.pdf", [{"qFrom": 1, "qTo": 9, "price": 9.601538462}, {"qFrom": 10, "qTo": 29, "price": 9.601538462}, {"qFrom": 30, "qTo": 199, "price": 9.601538462}, {"qFrom": 200, "qTo": 499, "price": 3.716923077}, {"qFrom": 500, "qTo": 999, "price": 3.586153846}, {"qFrom": 1000, "qTo": null, "price": 3.521538462}], [], "https://lcsc.com/product-detail/RF-attenuator_Analog-Devices-HMC802ALP3ETR_C662750.html", {"Frequency Range": {"format": "${default}", "primary": "default", "values": {"default": ["-", "string"]}}, "Attenuation Value": {"format": "${default}", "primary": "default", "values": {"default": ["-", "string"]}}, "Impedance": {"format": "${default}", "primary": "default", "values": {"default": ["-", "string"]}}, "Power": {"format": "${power}", "default": "power", "values": {"power": ["NaN", "power"]}}, "Basic/Extended": {"format": "${default}", "primary": "default", "values": {"default": ["Extended", "string"]}}, "Package": {"format": "${default}", "primary": "default", "values": {"default": ["SMT-16", "string"]}}, "Status": {"format": "${default}", "primary": "default", "values": {"default": ["-", "string"]}}}], ["C662564", "HMC305SLP4ETR", 25, "Analog Devices", "QFN-24(4x4) RF attenuator ROHS", "https://datasheet.lcsc.com/lcsc/2006241213_Analog-Devices-HMC305SLP4ETR_C662564.pdf", [{"qFrom": 1, "qTo": 9, "price": 18.793846154}, {"qFrom": 10, "qTo": 29, "price": 18.793846154}, {"qFrom": 30, "qTo": 199, "price": 18.793846154}, {"qFrom": 200, "qTo": 499, "price": 7.273846154}, {"qFrom": 500, "qTo": 999, "price": 7.018461538}, {"qFrom": 1000, "qTo": null, "price": 6.892307692}], [], "https://lcsc.com/product-detail/RF-attenuator_Analog-Devices-HMC305SLP4ETR_C662564.html", {"Frequency Range": {"format": "${default}", "primary": "default", "values": {"default": ["-", "string"]}}, "Attenuation Value": {"format": "${default}", "primary": "default", "values": {"default": ["-", "string"]}}, "Impedance": {"format": "${default}", "primary": "default", "values": {"default": ["-", "string"]}}, "Power": {"format": "${power}", "default": "power", "values": {"power": ["NaN", "power"]}}, "Basic/Extended": {"format": "${default}", "primary": "default", "values": {"default": ["Extended", "string"]}}, "Package": {"format": "${default}", "primary": "default", "values": {"default": ["QFN-24", "string"]}}, "Status": {"format": "${default}", "primary": "default", "values": {"default": ["-", "string"]}}}], ["C662332", "HMC470ATCPZ-EP-PT", 17, "Analog Devices", "LFCSP-16 RF attenuator ROHS", "https://datasheet.lcsc.com/lcsc/2006241209_Analog-Devices-HMC470ATCPZ-EP-PT_C662332.pdf", [{"qFrom": 1, "qTo": 9, "price": 36.358461538}, {"qFrom": 10, "qTo": 29, "price": 36.358461538}, {"qFrom": 30, "qTo": 199, "price": 36.358461538}, {"qFrom": 200, "qTo": 499, "price": 14.070769231}, {"qFrom": 500, "qTo": 999, "price": 13.576923077}, {"qFrom": 1000, "qTo": null, "price": 13.332307692}], [], "https://lcsc.com/product-detail/RF-attenuator_Analog-Devices-HMC470ATCPZ-EP-PT_C662332.html", {"Frequency Range": {"format": "${default}", "primary": "default", "values": {"default": ["-", "string"]}}, "Attenuation Value": {"format": "${default}", "primary": "default", "values": {"default": ["-", "string"]}}, "Impedance": {"format": "${default}", "primary": "default", "values": {"default": ["-", "string"]}}, "Power": {"format": "${power}", "default": "power", "values": {"power": ["NaN", "power"]}}, "Basic/Extended": {"format": "${default}", "primary": "default", "values": {"default": ["Extended", "string"]}}, "Package": {"format": "${default}", "primary": "default", "values": {"default": ["LFCSP-16", "string"]}}, "Status": {"format": "${default}", "primary": "default", "values": {"default": ["-", "string"]}}}], ["C662544", "HMC1095LP4ETR", 25, "Analog Devices", "SMT-24(4x4) RF attenuator ROHS", "https://datasheet.lcsc.com/lcsc/2006241308_Analog-Devices-HMC1095LP4ETR_C662544.pdf", [{"qFrom": 1, "qTo": 9, "price": 22.887692308}, {"qFrom": 10, "qTo": 29, "price": 22.887692308}, {"qFrom": 30, "qTo": 199, "price": 22.887692308}, {"qFrom": 200, "qTo": 499, "price": 8.856923077}, {"qFrom": 500, "qTo": 999, "price": 8.546153846}, {"qFrom": 1000, "qTo": null, "price": 8.392307692}], [], "https://lcsc.com/product-detail/RF-attenuator_Analog-Devices-HMC1095LP4ETR_C662544.html", {"Frequency Range": {"format": "${default}", "primary": "default", "values": {"default": ["-", "string"]}}, "Attenuation Value": {"format": "${default}", "primary": "default", "values": {"default": ["-", "string"]}}, "Impedance": {"format": "${default}", "primary": "default", "values": {"default": ["-", "string"]}}, "Power": {"format": "${power}", "default": "power", "values": {"power": ["NaN", "power"]}}, "Basic/Extended": {"format": "${default}", "primary": "default", "values": {"default": ["Extended", "string"]}}, "Package": {"format": "${default}", "primary": "default", "values": {"default": ["SMT-24", "string"]}}, "Status": {"format": "${default}", "primary": "default", "values": {"default": ["-", "string"]}}}], ["C662395", "HMC653LP2ETR", 7, "Analog Devices", "DFN-EP-6 RF attenuator ROHS", "https://datasheet.lcsc.com/lcsc/2006241210_Analog-Devices-HMC653LP2ETR_C662395.pdf", [{"qFrom": 1, "qTo": 9, "price": 11.043076923}, {"qFrom": 10, "qTo": 29, "price": 9.550769231}, {"qFrom": 30, "qTo": 99, "price": 9.276923077}, {"qFrom": 100, "qTo": 499, "price": 9.003076923}, {"qFrom": 500, "qTo": 999, "price": 8.881538462}, {"qFrom": 1000, "qTo": null, "price": 8.732307692}], [], "https://lcsc.com/product-detail/RF-attenuator_Analog-Devices-HMC653LP2ETR_C662395.html", {"Frequency Range": {"format": "${default}", "primary": "default", "values": {"default": ["-", "string"]}}, "Attenuation Value": {"format": "${default}", "primary": "default", "values": {"default": ["-", "string"]}}, "Impedance": {"format": "${default}", "primary": "default", "values": {"default": ["-", "string"]}}, "Power": {"format": "${power}", "default": "power", "values": {"power": ["NaN", "power"]}}, "Basic/Extended": {"format": "${default}", "primary": "default", "values": {"default": ["Extended", "string"]}}, "Package": {"format": "${default}", "primary": "default", "values": {"default": ["DFN-6", "string"]}}, "Status": {"format": "${default}", "primary": "default", "values": {"default": ["-", "string"]}}}], ["C662751", "HMC8073LP3DETR", 17, "Analog Devices", "LFCSP-16(3x3) RF attenuator ROHS", "https://datasheet.lcsc.com/lcsc/2006241609_Analog-Devices-HMC8073LP3DETR_C662751.pdf", [{"qFrom": 1, "qTo": 9, "price": 9.081538462}, {"qFrom": 10, "qTo": 29, "price": 9.081538462}, {"qFrom": 30, "qTo": 199, "price": 9.081538462}, {"qFrom": 200, "qTo": 499, "price": 3.515384615}, {"qFrom": 500, "qTo": 999, "price": 3.390769231}, {"qFrom": 1000, "qTo": null, "price": 3.330769231}], [], "https://lcsc.com/product-detail/RF-attenuator_Analog-Devices-HMC8073LP3DETR_C662751.html", {"Frequency Range": {"format": "${default}", "primary": "default", "values": {"default": ["-", "string"]}}, "Attenuation Value": {"format": "${default}", "primary": "default", "values": {"default": ["-", "string"]}}, "Impedance": {"format": "${default}", "primary": "default", "values": {"default": ["-", "string"]}}, "Power": {"format": "${power}", "default": "power", "values": {"power": ["NaN", "power"]}}, "Basic/Extended": {"format": "${default}", "primary": "default", "values": {"default": ["Extended", "string"]}}, "Package": {"format": "${default}", "primary": "default", "values": {"default": ["LFCSP-16", "string"]}}, "Status": {"format": "${default}", "primary": "default", "values": {"default": ["-", "string"]}}}], ["C662313", "HMC624ACPSZ-EP-RL7", 25, "Analog Devices", "LFCSP-24 RF attenuator ROHS", "https://datasheet.lcsc.com/lcsc/2006241209_Analog-Devices-HMC624ACPSZ-EP-RL7_C662313.pdf", [{"qFrom": 1, "qTo": 9, "price": 23.0}, {"qFrom": 10, "qTo": 29, "price": 23.0}, {"qFrom": 30, "qTo": 199, "price": 23.0}, {"qFrom": 200, "qTo": 499, "price": 8.901538462}, {"qFrom": 500, "qTo": 999, "price": 8.587692308}, {"qFrom": 1000, "qTo": null, "price": 8.433846154}], [], "https://lcsc.com/product-detail/RF-attenuator_Analog-Devices-HMC624ACPSZ-EP-RL7_C662313.html", {"Frequency Range": {"format": "${default}", "primary": "default", "values": {"default": ["-", "string"]}}, "Attenuation Value": {"format": "${default}", "primary": "default", "values": {"default": ["-", "string"]}}, "Impedance": {"format": "${default}", "primary": "default", "values": {"default": ["-", "string"]}}, "Power": {"format": "${power}", "default": "power", "values": {"power": ["NaN", "power"]}}, "Basic/Extended": {"format": "${default}", "primary": "default", "values": {"default": ["Extended", "string"]}}, "Package": {"format": "${default}", "primary": "default", "values": {"default": ["LFCSP-24", "string"]}}, "Status": {"format": "${default}", "primary": "default", "values": {"default": ["-", "string"]}}}], ["C659637", "ADRF5731BCCZN-R7", 17, "Analog Devices", "LGA-16 RF attenuator ROHS", "https://datasheet.lcsc.com/lcsc/2007131609_Analog-Devices-ADRF5731BCCZN-R7_C659637.pdf", [{"qFrom": 1, "qTo": 9, "price": 179.369230769}, {"qFrom": 10, "qTo": 29, "price": 155.347692308}, {"qFrom": 30, "qTo": 99, "price": 150.935384615}, {"qFrom": 100, "qTo": 499, "price": 146.523076923}, {"qFrom": 500, "qTo": 999, "price": 144.563076923}, {"qFrom": 1000, "qTo": null, "price": 142.14}], [], "https://lcsc.com/product-detail/RF-attenuator_Analog-Devices-ADRF5731BCCZN-R7_C659637.html", {"Frequency Range": {"format": "${default}", "primary": "default", "values": {"default": ["-", "string"]}}, "Attenuation Value": {"format": "${default}", "primary": "default", "values": {"default": ["-", "string"]}}, "Impedance": {"format": "${default}", "primary": "default", "values": {"default": ["-", "string"]}}, "Power": {"format": "${power}", "default": "power", "values": {"power": ["NaN", "power"]}}, "Basic/Extended": {"format": "${default}", "primary": "default", "values": {"default": ["Extended", "string"]}}, "Package": {"format": "${default}", "primary": "default", "values": {"default": ["LGA-16", "string"]}}, "Status": {"format": "${default}", "primary": "default", "values": {"default": ["-", "string"]}}}], ["C662333", "HMC470ATCPZ-EP-RL7", 17, "Analog Devices", "LFCSP-16 RF attenuator ROHS", "https://datasheet.lcsc.com/lcsc/2006241236_Analog-Devices-HMC470ATCPZ-EP-RL7_C662333.pdf", [{"qFrom": 1, "qTo": 9, "price": 36.358461538}, {"qFrom": 10, "qTo": 29, "price": 36.358461538}, {"qFrom": 30, "qTo": 199, "price": 36.358461538}, {"qFrom": 200, "qTo": 499, "price": 14.070769231}, {"qFrom": 500, "qTo": 999, "price": 13.576923077}, {"qFrom": 1000, "qTo": null, "price": 13.332307692}], [], "https://lcsc.com/product-detail/RF-attenuator_Analog-Devices-HMC470ATCPZ-EP-RL7_C662333.html", {"Frequency Range": {"format": "${default}", "primary": "default", "values": {"default": ["-", "string"]}}, "Attenuation Value": {"format": "${default}", "primary": "default", "values": {"default": ["-", "string"]}}, "Impedance": {"format": "${default}", "primary": "default", "values": {"default": ["-", "string"]}}, "Power": {"format": "${power}", "default": "power", "values": {"power": ["NaN", "power"]}}, "Basic/Extended": {"format": "${default}", "primary": "default", "values": {"default": ["Extended", "string"]}}, "Package": {"format": "${default}", "primary": "default", "values": {"default": ["LFCSP-16", "string"]}}, "Status": {"format": "${default}", "primary": "default", "values": {"default": ["-", "string"]}}}], ["C661812", "HMC759LP3ETR", 17, "Analog Devices", "QFN-16(3x3) RF attenuator ROHS", "https://datasheet.lcsc.com/lcsc/2006281816_Analog-Devices-HMC759LP3ETR_C661812.pdf", [{"qFrom": 1, "qTo": 9, "price": 13.658461538}, {"qFrom": 10, "qTo": 29, "price": 13.658461538}, {"qFrom": 30, "qTo": 199, "price": 13.658461538}, {"qFrom": 200, "qTo": 499, "price": 5.286153846}, {"qFrom": 500, "qTo": 999, "price": 5.1}, {"qFrom": 1000, "qTo": null, "price": 5.009230769}], [], "https://lcsc.com/product-detail/RF-attenuator_Analog-Devices-HMC759LP3ETR_C661812.html", {"Frequency Range": {"format": "${default}", "primary": "default", "values": {"default": ["-", "string"]}}, "Attenuation Value": {"format": "${default}", "primary": "default", "values": {"default": ["-", "string"]}}, "Impedance": {"format": "${default}", "primary": "default", "values": {"default": ["-", "string"]}}, "Power": {"format": "${power}", "default": "power", "values": {"power": ["NaN", "power"]}}, "Basic/Extended": {"format": "${default}", "primary": "default", "values": {"default": ["Extended", "string"]}}, "Package": {"format": "${default}", "primary": "default", "values": {"default": ["QFN-16", "string"]}}, "Status": {"format": "${default}", "primary": "default", "values": {"default": ["-", "string"]}}}], ["C662396", "HMC654LP2ETR", 7, "Analog Devices", "DFN-EP-6 RF attenuator ROHS", "https://datasheet.lcsc.com/lcsc/2006241210_Analog-Devices-HMC654LP2ETR_C662396.pdf", [{"qFrom": 1, "qTo": 9, "price": 10.446153846}, {"qFrom": 10, "qTo": 29, "price": 9.035384615}, {"qFrom": 30, "qTo": 99, "price": 8.776923077}, {"qFrom": 100, "qTo": 499, "price": 8.516923077}, {"qFrom": 500, "qTo": 999, "price": 8.401538462}, {"qFrom": 1000, "qTo": null, "price": 8.26}], [], "https://lcsc.com/product-detail/RF-attenuator_Analog-Devices-HMC654LP2ETR_C662396.html", {"Frequency Range": {"format": "${default}", "primary": "default", "values": {"default": ["-", "string"]}}, "Attenuation Value": {"format": "${default}", "primary": "default", "values": {"default": ["-", "string"]}}, "Impedance": {"format": "${default}", "primary": "default", "values": {"default": ["-", "string"]}}, "Power": {"format": "${power}", "default": "power", "values": {"power": ["NaN", "power"]}}, "Basic/Extended": {"format": "${default}", "primary": "default", "values": {"default": ["Extended", "string"]}}, "Package": {"format": "${default}", "primary": "default", "values": {"default": ["DFN-6", "string"]}}, "Status": {"format": "${default}", "primary": "default", "values": {"default": ["-", "string"]}}}], ["C662588", "HMC424ALP3ETR", 17, "Analog Devices", "SMT-16(3x3) RF attenuator ROHS", "https://datasheet.lcsc.com/lcsc/2006241334_Analog-Devices-HMC424ALP3ETR_C662588.pdf", [{"qFrom": 1, "qTo": 9, "price": 50.313846154}, {"qFrom": 10, "qTo": 29, "price": 50.313846154}, {"qFrom": 30, "qTo": 199, "price": 50.313846154}, {"qFrom": 200, "qTo": 499, "price": 19.472307692}, {"qFrom": 500, "qTo": 999, "price": 18.787692308}, {"qFrom": 1000, "qTo": null, "price": 18.449230769}], [], "https://lcsc.com/product-detail/RF-attenuator_Analog-Devices-HMC424ALP3ETR_C662588.html", {"Frequency Range": {"format": "${default}", "primary": "default", "values": {"default": ["-", "string"]}}, "Attenuation Value": {"format": "${default}", "primary": "default", "values": {"default": ["-", "string"]}}, "Impedance": {"format": "${default}", "primary": "default", "values": {"default": ["-", "string"]}}, "Power": {"format": "${power}", "default": "power", "values": {"power": ["NaN", "power"]}}, "Basic/Extended": {"format": "${default}", "primary": "default", "values": {"default": ["Extended", "string"]}}, "Package": {"format": "${default}", "primary": "default", "values": {"default": ["SMT-16", "string"]}}, "Status": {"format": "${default}", "primary": "default", "values": {"default": ["-", "string"]}}}], ["C662625", "HMC539ALP3ETR", 17, "Analog Devices", "SMT-16(3x3) RF attenuator ROHS", "https://datasheet.lcsc.com/lcsc/2006241335_Analog-Devices-HMC539ALP3ETR_C662625.pdf", [{"qFrom": 1, "qTo": 9, "price": 16.895384615}, {"qFrom": 10, "qTo": 29, "price": 16.895384615}, {"qFrom": 30, "qTo": 199, "price": 16.895384615}, {"qFrom": 200, "qTo": 499, "price": 6.538461538}, {"qFrom": 500, "qTo": 999, "price": 6.309230769}, {"qFrom": 1000, "qTo": null, "price": 6.195384615}], [], "https://lcsc.com/product-detail/RF-attenuator_Analog-Devices-HMC539ALP3ETR_C662625.html", {"Frequency Range": {"format": "${default}", "primary": "default", "values": {"default": ["-", "string"]}}, "Attenuation Value": {"format": "${default}", "primary": "default", "values": {"default": ["-", "string"]}}, "Impedance": {"format": "${default}", "primary": "default", "values": {"default": ["-", "string"]}}, "Power": {"format": "${power}", "default": "power", "values": {"power": ["NaN", "power"]}}, "Basic/Extended": {"format": "${default}", "primary": "default", "values": {"default": ["Extended", "string"]}}, "Package": {"format": "${default}", "primary": "default", "values": {"default": ["SMT-16", "string"]}}, "Status": {"format": "${default}", "primary": "default", "values": {"default": ["-", "string"]}}}], ["C662626", "HMC539ALP3TR", 17, "Analog Devices", "SMT-16(3x3) RF attenuator ROHS", "https://datasheet.lcsc.com/lcsc/2006241335_Analog-Devices-HMC539ALP3TR_C662626.pdf", [{"qFrom": 1, "qTo": 9, "price": 21.547692308}, {"qFrom": 10, "qTo": 29, "price": 21.547692308}, {"qFrom": 30, "qTo": 199, "price": 21.547692308}, {"qFrom": 200, "qTo": 499, "price": 8.338461538}, {"qFrom": 500, "qTo": 999, "price": 8.046153846}, {"qFrom": 1000, "qTo": null, "price": 7.901538462}], [], "https://lcsc.com/product-detail/RF-attenuator_Analog-Devices-HMC539ALP3TR_C662626.html", {"Frequency Range": {"format": "${default}", "primary": "default", "values": {"default": ["-", "string"]}}, "Attenuation Value": {"format": "${default}", "primary": "default", "values": {"default": ["-", "string"]}}, "Impedance": {"format": "${default}", "primary": "default", "values": {"default": ["-", "string"]}}, "Power": {"format": "${power}", "default": "power", "values": {"power": ["NaN", "power"]}}, "Basic/Extended": {"format": "${default}", "primary": "default", "values": {"default": ["Extended", "string"]}}, "Package": {"format": "${default}", "primary": "default", "values": {"default": ["SMT-16", "string"]}}, "Status": {"format": "${default}", "primary": "default", "values": {"default": ["-", "string"]}}}], ["C662563", "HMC291SETR", 6, "Analog Devices", "SOT-26 RF attenuator ROHS", "https://datasheet.lcsc.com/lcsc/2006241213_Analog-Devices-HMC291SETR_C662563.pdf", [{"qFrom": 1, "qTo": 9, "price": 8.3}, {"qFrom": 10, "qTo": 29, "price": 8.3}, {"qFrom": 30, "qTo": 199, "price": 8.3}, {"qFrom": 200, "qTo": 499, "price": 3.212307692}, {"qFrom": 500, "qTo": 999, "price": 3.1}, {"qFrom": 1000, "qTo": null, "price": 3.043076923}], [], "https://lcsc.com/product-detail/RF-attenuator_Analog-Devices-HMC291SETR_C662563.html", {"Frequency Range": {"format": "${default}", "primary": "default", "values": {"default": ["-", "string"]}}, "Attenuation Value": {"format": "${default}", "primary": "default", "values": {"default": ["-", "string"]}}, "Impedance": {"format": "${default}", "primary": "default", "values": {"default": ["-", "string"]}}, "Power": {"format": "${power}", "default": "power", "values": {"power": ["NaN", "power"]}}, "Basic/Extended": {"format": "${default}", "primary": "default", "values": {"default": ["Extended", "string"]}}, "Package": {"format": "${default}", "primary": "default", "values": {"default": ["SOT-26", "string"]}}, "Status": {"format": "${default}", "primary": "default", "values": {"default": ["-", "string"]}}}], ["C662331", "HMC346ALP3ETR", 17, "Analog Devices", "SMT-16 RF attenuator ROHS", "https://datasheet.lcsc.com/lcsc/2006241209_Analog-Devices-HMC346ALP3ETR_C662331.pdf", [{"qFrom": 1, "qTo": 9, "price": 63.749230769}, {"qFrom": 10, "qTo": 29, "price": 63.749230769}, {"qFrom": 30, "qTo": 199, "price": 63.749230769}, {"qFrom": 200, "qTo": 499, "price": 24.670769231}, {"qFrom": 500, "qTo": 999, "price": 23.803076923}, {"qFrom": 1000, "qTo": null, "price": 23.375384615}], [], "https://lcsc.com/product-detail/RF-attenuator_Analog-Devices-HMC346ALP3ETR_C662331.html", {"Frequency Range": {"format": "${default}", "primary": "default", "values": {"default": ["-", "string"]}}, "Attenuation Value": {"format": "${default}", "primary": "default", "values": {"default": ["-", "string"]}}, "Impedance": {"format": "${default}", "primary": "default", "values": {"default": ["-", "string"]}}, "Power": {"format": "${power}", "default": "power", "values": {"power": ["NaN", "power"]}}, "Basic/Extended": {"format": "${default}", "primary": "default", "values": {"default": ["Extended", "string"]}}, "Package": {"format": "${default}", "primary": "default", "values": {"default": ["SMT-16", "string"]}}, "Status": {"format": "${default}", "primary": "default", "values": {"default": ["-", "string"]}}}], ["C662394", "HMC652LP2ETR", 7, "Analog Devices", "DFN-EP-6 RF attenuator ROHS", "https://datasheet.lcsc.com/lcsc/2006241237_Analog-Devices-HMC652LP2ETR_C662394.pdf", [{"qFrom": 1, "qTo": 9, "price": 13.324615385}, {"qFrom": 10, "qTo": 29, "price": 11.524615385}, {"qFrom": 30, "qTo": 99, "price": 11.195384615}, {"qFrom": 100, "qTo": 499, "price": 10.864615385}, {"qFrom": 500, "qTo": 999, "price": 10.716923077}, {"qFrom": 1000, "qTo": null, "price": 10.535384615}], ["https://assets.lcsc.com/images/lcsc/900x900/20210810_Analog-Devices-HMC652LP2ETR_C662394_back.jpg", "https://assets.lcsc.com/images/lcsc/900x900/20210810_Analog-Devices-HMC652LP2ETR_C662394_blank.jpg", "https://assets.lcsc.com/images/lcsc/900x900/20210810_Analog-Devices-HMC652LP2ETR_C662394_front.jpg"], "https://lcsc.com/product-detail/RF-attenuator_Analog-Devices-HMC652LP2ETR_C662394.html", {"Frequency Range": {"format": "${default}", "primary": "default", "values": {"default": ["-", "string"]}}, "Attenuation Value": {"format": "${default}", "primary": "default", "values": {"default": ["-", "string"]}}, "Impedance": {"format": "${default}", "primary": "default", "values": {"default": ["-", "string"]}}, "Power": {"format": "${power}", "default": "power", "values": {"power": ["NaN", "power"]}}, "Basic/Extended": {"format": "${default}", "primary": "default", "values": {"default": ["Extended", "string"]}}, "Package": {"format": "${default}", "primary": "default", "values": {"default": ["DFN-6", "string"]}}, "Status": {"format": "${default}", "primary": "default", "values": {"default": ["-", "string"]}}}], ["C661890", "HMC792ALP4ETR", 25, "Analog Devices", "QFN-24 RF attenuator ROHS", "https://datasheet.lcsc.com/lcsc/2006281837_Analog-Devices-HMC792ALP4ETR_C661890.pdf", [{"qFrom": 1, "qTo": 9, "price": 34.052307692}, {"qFrom": 10, "qTo": 29, "price": 34.052307692}, {"qFrom": 30, "qTo": 199, "price": 34.052307692}, {"qFrom": 200, "qTo": 499, "price": 13.178461538}, {"qFrom": 500, "qTo": 999, "price": 12.715384615}, {"qFrom": 1000, "qTo": null, "price": 12.486153846}], [], "https://lcsc.com/product-detail/RF-attenuator_Analog-Devices-HMC792ALP4ETR_C661890.html", {"Frequency Range": {"format": "${default}", "primary": "default", "values": {"default": ["-", "string"]}}, "Attenuation Value": {"format": "${default}", "primary": "default", "values": {"default": ["-", "string"]}}, "Impedance": {"format": "${default}", "primary": "default", "values": {"default": ["-", "string"]}}, "Power": {"format": "${power}", "default": "power", "values": {"power": ["NaN", "power"]}}, "Basic/Extended": {"format": "${default}", "primary": "default", "values": {"default": ["Extended", "string"]}}, "Package": {"format": "${default}", "primary": "default", "values": {"default": ["QFN-24", "string"]}}, "Status": {"format": "${default}", "primary": "default", "values": {"default": ["-", "string"]}}}], ["C494495", "HMC425ALP3ETR", 17, "Analog Devices", "LFCSP-16 RF attenuator ROHS", "https://datasheet.lcsc.com/lcsc/2003091237_Analog-Devices-HMC425ALP3ETR_C494495.pdf", [{"qFrom": 1, "qTo": 9, "price": 8.024615385}, {"qFrom": 10, "qTo": 29, "price": 7.009230769}, {"qFrom": 30, "qTo": 99, "price": 6.823076923}, {"qFrom": 100, "qTo": 499, "price": 6.636923077}, {"qFrom": 500, "qTo": 999, "price": 6.553846154}, {"qFrom": 1000, "qTo": 1999, "price": 6.450769231}, {"qFrom": 2000, "qTo": 3999, "price": 6.375384615}, {"qFrom": 4000, "qTo": null, "price": 6.324615385}], ["https://assets.lcsc.com/images/lcsc/900x900/20200323_Analog-Devices-HMC425ALP3ETR_C494495_front.jpg", "https://assets.lcsc.com/images/lcsc/900x900/20200323_Analog-Devices-HMC425ALP3ETR_C494495_back.jpg", "https://assets.lcsc.com/images/lcsc/900x900/20200323_Analog-Devices-HMC425ALP3ETR_C494495_blank.jpg"], "https://lcsc.com/product-detail/RF-attenuator_Analog-Devices-HMC425ALP3ETR_C494495.html", {"Frequency Range": {"format": "${default}", "primary": "default", "values": {"default": ["-", "string"]}}, "Attenuation Value": {"format": "${default}", "primary": "default", "values": {"default": ["-", "string"]}}, "Impedance": {"format": "${default}", "primary": "default", "values": {"default": ["-", "string"]}}, "Power": {"format": "${power}", "default": "power", "values": {"power": ["NaN", "power"]}}, "Basic/Extended": {"format": "${default}", "primary": "default", "values": {"default": ["Extended", "string"]}}, "Package": {"format": "${default}", "primary": "default", "values": {"default": ["LFCSP-16", "string"]}}, "Status": {"format": "${default}", "primary": "default", "values": {"default": ["-", "string"]}}}], ["C662314", "HMC624ALP4ETR", 25, "Analog Devices", "LFCSP-24 RF attenuator ROHS", "https://datasheet.lcsc.com/lcsc/2006241209_Analog-Devices-HMC624ALP4ETR_C662314.pdf", [{"qFrom": 1, "qTo": 9, "price": 6.947692308}, {"qFrom": 10, "qTo": 29, "price": 5.987692308}, {"qFrom": 30, "qTo": 99, "price": 5.812307692}, {"qFrom": 100, "qTo": 499, "price": 5.635384615}, {"qFrom": 500, "qTo": 999, "price": 5.556923077}, {"qFrom": 1000, "qTo": null, "price": 5.46}], ["https://assets.lcsc.com/images/lcsc/900x900/20210413_Analog-Devices-HMC624ALP4ETR_C662314_front.jpg", "https://assets.lcsc.com/images/lcsc/900x900/20210413_Analog-Devices-HMC624ALP4ETR_C662314_back.jpg", "https://assets.lcsc.com/images/lcsc/900x900/20210413_Analog-Devices-HMC624ALP4ETR_C662314_blank.jpg"], "https://lcsc.com/product-detail/RF-attenuator_Analog-Devices-HMC624ALP4ETR_C662314.html", {"Frequency Range": {"format": "${default}", "primary": "default", "values": {"default": ["-", "string"]}}, "Attenuation Value": {"format": "${default}", "primary": "default", "values": {"default": ["-", "string"]}}, "Impedance": {"format": "${default}", "primary": "default", "values": {"default": ["-", "string"]}}, "Power": {"format": "${power}", "default": "power", "values": {"power": ["NaN", "power"]}}, "Basic/Extended": {"format": "${default}", "primary": "default", "values": {"default": ["Extended", "string"]}}, "Package": {"format": "${default}", "primary": "default", "values": {"default": ["LFCSP-24", "string"]}}, "Status": {"format": "${default}", "primary": "default", "values": {"default": ["-", "string"]}}}], ["C662334", "HMC712ALP3CETR", 17, "Analog Devices", "SMT-16(3x3) RF attenuator ROHS", "https://datasheet.lcsc.com/lcsc/2006241333_Analog-Devices-HMC712ALP3CETR_C662334.pdf", [{"qFrom": 1, "qTo": 9, "price": 84.476923077}, {"qFrom": 10, "qTo": 29, "price": 84.476923077}, {"qFrom": 30, "qTo": 199, "price": 84.476923077}, {"qFrom": 200, "qTo": 499, "price": 32.692307692}, {"qFrom": 500, "qTo": 999, "price": 31.543076923}, {"qFrom": 1000, "qTo": null, "price": 30.975384615}], [], "https://lcsc.com/product-detail/RF-attenuator_Analog-Devices-HMC712ALP3CETR_C662334.html", {"Frequency Range": {"format": "${default}", "primary": "default", "values": {"default": ["-", "string"]}}, "Attenuation Value": {"format": "${default}", "primary": "default", "values": {"default": ["-", "string"]}}, "Impedance": {"format": "${default}", "primary": "default", "values": {"default": ["-", "string"]}}, "Power": {"format": "${power}", "default": "power", "values": {"power": ["NaN", "power"]}}, "Basic/Extended": {"format": "${default}", "primary": "default", "values": {"default": ["Extended", "string"]}}, "Package": {"format": "${default}", "primary": "default", "values": {"default": ["SMT-16", "string"]}}, "Status": {"format": "${default}", "primary": "default", "values": {"default": ["-", "string"]}}}], ["C662397", "HMC656LP2ETR", 7, "Analog Devices", "DFN-EP-6 RF attenuator ROHS", "https://datasheet.lcsc.com/lcsc/2006241210_Analog-Devices-HMC656LP2ETR_C662397.pdf", [{"qFrom": 1, "qTo": 9, "price": 9.229230769}, {"qFrom": 10, "qTo": 29, "price": 9.229230769}, {"qFrom": 30, "qTo": 199, "price": 9.229230769}, {"qFrom": 200, "qTo": 499, "price": 3.572307692}, {"qFrom": 500, "qTo": 999, "price": 3.446153846}, {"qFrom": 1000, "qTo": null, "price": 3.384615385}], [], "https://lcsc.com/product-detail/RF-attenuator_Analog-Devices-HMC656LP2ETR_C662397.html", {"Frequency Range": {"format": "${default}", "primary": "default", "values": {"default": ["-", "string"]}}, "Attenuation Value": {"format": "${default}", "primary": "default", "values": {"default": ["-", "string"]}}, "Impedance": {"format": "${default}", "primary": "default", "values": {"default": ["-", "string"]}}, "Power": {"format": "${power}", "default": "power", "values": {"power": ["NaN", "power"]}}, "Basic/Extended": {"format": "${default}", "primary": "default", "values": {"default": ["Extended", "string"]}}, "Package": {"format": "${default}", "primary": "default", "values": {"default": ["DFN-6", "string"]}}, "Status": {"format": "${default}", "primary": "default", "values": {"default": ["-", "string"]}}}], ["C661891", "HMC812ALC4TR", 25, "Analog Devices", "CSTM-24(4x4) RF attenuator ROHS", "https://datasheet.lcsc.com/lcsc/2006281821_Analog-Devices-HMC812ALC4TR_C661891.pdf", [{"qFrom": 1, "qTo": 9, "price": 136.838461538}, {"qFrom": 10, "qTo": 29, "price": 136.838461538}, {"qFrom": 30, "qTo": 199, "price": 136.838461538}, {"qFrom": 200, "qTo": 499, "price": 52.955384615}, {"qFrom": 500, "qTo": 999, "price": 51.093846154}, {"qFrom": 1000, "qTo": null, "price": 50.173846154}], [], "https://lcsc.com/product-detail/RF-attenuator_Analog-Devices-HMC812ALC4TR_C661891.html", {"Frequency Range": {"format": "${default}", "primary": "default", "values": {"default": ["-", "string"]}}, "Attenuation Value": {"format": "${default}", "primary": "default", "values": {"default": ["-", "string"]}}, "Impedance": {"format": "${default}", "primary": "default", "values": {"default": ["-", "string"]}}, "Power": {"format": "${power}", "default": "power", "values": {"power": ["NaN", "power"]}}, "Basic/Extended": {"format": "${default}", "primary": "default", "values": {"default": ["Extended", "string"]}}, "Package": {"format": "${default}", "primary": "default", "values": {"default": ["CSMT-24", "string"]}}, "Status": {"format": "${default}", "primary": "default", "values": {"default": ["-", "string"]}}}], ["C662137", "HMC346AMS8GETR", 9, "Analog Devices", "MSOP-8 RF attenuator ROHS", "https://datasheet.lcsc.com/lcsc/2006241739_Analog-Devices-HMC346AMS8GETR_C662137.pdf", [{"qFrom": 1, "qTo": 9, "price": 13.1}, {"qFrom": 10, "qTo": 29, "price": 13.1}, {"qFrom": 30, "qTo": 199, "price": 13.1}, {"qFrom": 200, "qTo": 499, "price": 5.070769231}, {"qFrom": 500, "qTo": 999, "price": 4.892307692}, {"qFrom": 1000, "qTo": null, "price": 4.804615385}], [], "https://lcsc.com/product-detail/RF-attenuator_Analog-Devices-HMC346AMS8GETR_C662137.html", {"Frequency Range": {"format": "${default}", "primary": "default", "values": {"default": ["-", "string"]}}, "Attenuation Value": {"format": "${default}", "primary": "default", "values": {"default": ["-", "string"]}}, "Impedance": {"format": "${default}", "primary": "default", "values": {"default": ["-", "string"]}}, "Power": {"format": "${power}", "default": "power", "values": {"power": ["NaN", "power"]}}, "Basic/Extended": {"format": "${default}", "primary": "default", "values": {"default": ["Extended", "string"]}}, "Package": {"format": "${default}", "primary": "default", "values": {"default": ["MSOP-8", "string"]}}, "Status": {"format": "${default}", "primary": "default", "values": {"default": ["-", "string"]}}}], ["C514397", "HMC470ALP3ETR", 17, "Analog Devices", "LFCSP-16 RF attenuator ROHS", "https://datasheet.lcsc.com/lcsc/2004261534_Analog-Devices-HMC470ALP3ETR_C514397.pdf", [{"qFrom": 1, "qTo": 9, "price": 3.983076923}, {"qFrom": 10, "qTo": 29, "price": 3.446153846}, {"qFrom": 30, "qTo": 99, "price": 3.347692308}, {"qFrom": 100, "qTo": 499, "price": 3.247692308}, {"qFrom": 500, "qTo": 999, "price": 3.204615385}, {"qFrom": 1000, "qTo": 1999, "price": 3.150769231}, {"qFrom": 2000, "qTo": 3999, "price": 3.109230769}, {"qFrom": 4000, "qTo": null, "price": 3.083076923}], ["https://assets.lcsc.com/images/lcsc/900x900/20200519_Analog-Devices-HMC470ALP3ETR_C514397_front.jpg", "https://assets.lcsc.com/images/lcsc/900x900/20200519_Analog-Devices-HMC470ALP3ETR_C514397_back.jpg", "https://assets.lcsc.com/images/lcsc/900x900/20200519_Analog-Devices-HMC470ALP3ETR_C514397_blank.jpg"], "https://lcsc.com/product-detail/RF-attenuator_Analog-Devices-HMC470ALP3ETR_C514397.html", {"Frequency Range": {"format": "${default}", "primary": "default", "values": {"default": ["-", "string"]}}, "Attenuation Value": {"format": "${default}", "primary": "default", "values": {"default": ["-", "string"]}}, "Impedance": {"format": "${default}", "primary": "default", "values": {"default": ["-", "string"]}}, "Power": {"format": "${power}", "default": "power", "values": {"power": ["NaN", "power"]}}, "Basic/Extended": {"format": "${default}", "primary": "default", "values": {"default": ["Extended", "string"]}}, "Package": {"format": "${default}", "primary": "default", "values": {"default": ["LFCSP-16", "string"]}}, "Status": {"format": "${default}", "primary": "default", "values": {"default": ["-", "string"]}}}], ["C662546", "HMC1119LP4METR", 25, "Analog Devices", "LFCSP-24(4x4) RF attenuator ROHS", "https://datasheet.lcsc.com/lcsc/2006241213_Analog-Devices-HMC1119LP4METR_C662546.pdf", [{"qFrom": 1, "qTo": 9, "price": 5.598461538}, {"qFrom": 10, "qTo": 29, "price": 4.841538462}, {"qFrom": 30, "qTo": 99, "price": 4.703076923}, {"qFrom": 100, "qTo": 499, "price": 4.564615385}, {"qFrom": 500, "qTo": 999, "price": 4.503076923}, {"qFrom": 1000, "qTo": null, "price": 4.426153846}], ["https://assets.lcsc.com/images/lcsc/900x900/20210419_Analog-Devices-HMC1119LP4METR_C662546_front.jpg", "https://assets.lcsc.com/images/lcsc/900x900/20210419_Analog-Devices-HMC1119LP4METR_C662546_back.jpg", "https://assets.lcsc.com/images/lcsc/900x900/20210419_Analog-Devices-HMC1119LP4METR_C662546_blank.jpg"], "https://lcsc.com/product-detail/RF-attenuator_Analog-Devices-HMC1119LP4METR_C662546.html", {"Frequency Range": {"format": "${default}", "primary": "default", "values": {"default": ["-", "string"]}}, "Attenuation Value": {"format": "${default}", "primary": "default", "values": {"default": ["-", "string"]}}, "Impedance": {"format": "${default}", "primary": "default", "values": {"default": ["-", "string"]}}, "Power": {"format": "${power}", "default": "power", "values": {"power": ["NaN", "power"]}}, "Basic/Extended": {"format": "${default}", "primary": "default", "values": {"default": ["Extended", "string"]}}, "Package": {"format": "${default}", "primary": "default", "values": {"default": ["LFCSP-24", "string"]}}, "Status": {"format": "${default}", "primary": "default", "values": {"default": ["-", "string"]}}}], ["C481892", "HMC1122LP4METR", 24, "Analog Devices", "VFQFN-24 RF attenuator ROHS", "https://datasheet.lcsc.com/lcsc/2001131709_Analog-Devices-HMC1122LP4METR_C481892.pdf", [{"qFrom": 1, "qTo": 9, "price": 3.830769231}, {"qFrom": 10, "qTo": 29, "price": 2.772307692}, {"qFrom": 30, "qTo": 99, "price": 2.578461538}, {"qFrom": 100, "qTo": 499, "price": 2.383076923}, {"qFrom": 500, "qTo": 999, "price": 2.296923077}, {"qFrom": 1000, "qTo": 1999, "price": 2.255384615}, {"qFrom": 2000, "qTo": 3999, "price": 2.223076923}, {"qFrom": 4000, "qTo": null, "price": 2.201538462}], ["https://assets.lcsc.com/images/lcsc/900x900/20200306_Analog-Devices-HMC1122LP4METR_C481892_front.jpg", "https://assets.lcsc.com/images/lcsc/900x900/20200306_Analog-Devices-HMC1122LP4METR_C481892_back.jpg", "https://assets.lcsc.com/images/lcsc/900x900/20200306_Analog-Devices-HMC1122LP4METR_C481892_blank.jpg"], "https://lcsc.com/product-detail/RF-attenuator_Analog-Devices-HMC1122LP4METR_C481892.html", {"Frequency Range": {"format": "${default}", "primary": "default", "values": {"default": ["-", "string"]}}, "Attenuation Value": {"format": "${default}", "primary": "default", "values": {"default": ["-", "string"]}}, "Impedance": {"format": "${default}", "primary": "default", "values": {"default": ["-", "string"]}}, "Power": {"format": "${power}", "default": "power", "values": {"power": ["NaN", "power"]}}, "Basic/Extended": {"format": "${default}", "primary": "default", "values": {"default": ["Extended", "string"]}}, "Package": {"format": "${default}", "primary": "default", "values": {"default": ["QFN-24", "string"]}}, "Status": {"format": "${default}", "primary": "default", "values": {"default": ["-", "string"]}}}], ["C514410", "HMC985ALP4KE", 25, "Analog Devices", "SMT-24 RF attenuator ROHS", "https://datasheet.lcsc.com/lcsc/2105241239_Analog-Devices-HMC985ALP4KE_C514410.pdf", [{"qFrom": 1, "qTo": 9, "price": 45.575384615}, {"qFrom": 10, "qTo": 29, "price": 44.761538462}, {"qFrom": 30, "qTo": 99, "price": 44.761538462}, {"qFrom": 100, "qTo": 499, "price": 44.761538462}, {"qFrom": 500, "qTo": 999, "price": 44.761538462}, {"qFrom": 1000, "qTo": null, "price": 44.761538462}], ["https://assets.lcsc.com/images/lcsc/900x900/20210205_Analog-Devices-HMC985ALP4KE_C514410_front.jpg", "https://assets.lcsc.com/images/lcsc/900x900/20210205_Analog-Devices-HMC985ALP4KE_C514410_back.jpg", "https://assets.lcsc.com/images/lcsc/900x900/20210205_Analog-Devices-HMC985ALP4KE_C514410_blank.jpg"], "https://lcsc.com/product-detail/RF-attenuator_Analog-Devices-HMC985ALP4KE_C514410.html", {"Frequency Range": {"format": "${default}", "primary": "default", "values": {"default": ["-", "string"]}}, "Attenuation Value": {"format": "${default}", "primary": "default", "values": {"default": ["-", "string"]}}, "Impedance": {"format": "${default}", "primary": "default", "values": {"default": ["-", "string"]}}, "Power": {"format": "${power}", "default": "power", "values": {"power": ["NaN", "power"]}}, "Basic/Extended": {"format": "${default}", "primary": "default", "values": {"default": ["Extended", "string"]}}, "Package": {"format": "${default}", "primary": "default", "values": {"default": ["SMT-24", "string"]}}, "Status": {"format": "${default}", "primary": "default", "values": {"default": ["-", "string"]}}}], ["C579563", "HMC629ALP4ETR", 25, "Analog Devices", "VFQFN-24 RF attenuator ROHS", "https://datasheet.lcsc.com/lcsc/2009011505_Analog-Devices-HMC629ALP4ETR_C579563.pdf", [{"qFrom": 1, "qTo": 9, "price": 14.272307692}, {"qFrom": 10, "qTo": 29, "price": 12.321538462}, {"qFrom": 30, "qTo": 99, "price": 11.963076923}, {"qFrom": 100, "qTo": 499, "price": 11.604615385}, {"qFrom": 500, "qTo": 999, "price": 11.444615385}, {"qFrom": 1000, "qTo": null, "price": 11.247692308}], ["https://assets.lcsc.com/images/lcsc/900x900/20200829_Analog-Devices-HMC629ALP4ETR_C579563_front.jpg", "https://assets.lcsc.com/images/lcsc/900x900/20200829_Analog-Devices-HMC629ALP4ETR_C579563_back.jpg", "https://assets.lcsc.com/images/lcsc/900x900/20200829_Analog-Devices-HMC629ALP4ETR_C579563_blank.jpg"], "https://lcsc.com/product-detail/RF-attenuator_Analog-Devices-HMC629ALP4ETR_C579563.html", {"Frequency Range": {"format": "${default}", "primary": "default", "values": {"default": ["-", "string"]}}, "Attenuation Value": {"format": "${default}", "primary": "default", "values": {"default": ["-", "string"]}}, "Impedance": {"format": "${default}", "primary": "default", "values": {"default": ["-", "string"]}}, "Power": {"format": "${power}", "default": "power", "values": {"power": ["NaN", "power"]}}, "Basic/Extended": {"format": "${default}", "primary": "default", "values": {"default": ["Extended", "string"]}}, "Package": {"format": "${default}", "primary": "default", "values": {"default": ["VQFN-24", "string"]}}, "Status": {"format": "${default}", "primary": "default", "values": {"default": ["-", "string"]}}}], ["C2151339", "PAT0510S-C-9DB-T10", 4, "SUSUMU", "0402 RF attenuator ROHS", " ", [{"qFrom": 1, "qTo": 9, "price": 0.062153846}, {"qFrom": 10, "qTo": 29, "price": 0.062153846}, {"qFrom": 30, "qTo": 199, "price": 0.062153846}, {"qFrom": 200, "qTo": 499, "price": 0.024}, {"qFrom": 500, "qTo": 999, "price": 0.023230769}, {"qFrom": 1000, "qTo": null, "price": 0.022769231}], [], "https://lcsc.com/product-detail/RF-attenuator_SUSUMU-PAT0510S-C-9DB-T10_C2151339.html", {"Frequency Range": {"format": "${default}", "primary": "default", "values": {"default": ["-", "string"]}}, "Attenuation Value": {"format": "${default}", "primary": "default", "values": {"default": ["-", "string"]}}, "Impedance": {"format": "${default}", "primary": "default", "values": {"default": ["-", "string"]}}, "Power": {"format": "${power}", "default": "power", "values": {"power": ["NaN", "power"]}}, "Basic/Extended": {"format": "${default}", "primary": "default", "values": {"default": ["Extended", "string"]}}, "Package": {"format": "${default}", "primary": "default", "values": {"default": ["0402", "string"]}}, "Status": {"format": "${default}", "primary": "default", "values": {"default": ["-", "string"]}}}]], "category": "RF & Radio", "subcategory": "RF attenuator"}